spelltinkle/__init__.py
spelltinkle/__main__.py
spelltinkle/backup.py
spelltinkle/calender.py
spelltinkle/choise.py
spelltinkle/cli_complete.py
spelltinkle/color.py
spelltinkle/command.py
spelltinkle/complete.py
spelltinkle/config.py
spelltinkle/cursors.py
spelltinkle/document.py
spelltinkle/exceptions.py
spelltinkle/execute.py
spelltinkle/extract_variable.py
spelltinkle/fileinput.py
spelltinkle/filelist.py
spelltinkle/help.py
spelltinkle/history.py
spelltinkle/i18n.py
spelltinkle/input.py
spelltinkle/keys.py
spelltinkle/logo.py
spelltinkle/move_to_character.py
spelltinkle/notes.py
spelltinkle/replace.py
spelltinkle/resize.py
spelltinkle/rest.py
spelltinkle/run.py
spelltinkle/run_unittest.py
spelltinkle/screen.py
spelltinkle/search.py
spelltinkle/session.py
spelltinkle/spellcheck.py
spelltinkle/text.py
spelltinkle/utils.py
spelltinkle/view.py
spelltinkle/mail/__init__.py
spelltinkle/mail/addresses.py
spelltinkle/mail/document.py
spelltinkle/mail/email.py
spelltinkle/mail/folder.py
spelltinkle/mail/server.py
spelltinkle/mail/test.py
spelltinkle/test/__init__.py
spelltinkle/test/conftest.py
spelltinkle/test/cursors_test.py
spelltinkle/test/execute_test.py
spelltinkle/test/spellcheck_test.py
spelltinkle/test/test_calender.py
spelltinkle/test/test_cli_complete.py
spelltinkle/test/test_integration.py
spelltinkle/test/test_isort.py
spelltinkle/test/test_mail.py
spelltinkle-25.6.0.dist-info/licenses/LICENSE
spelltinkle-25.6.0.dist-info/METADATA
spelltinkle-25.6.0.dist-info/WHEEL
spelltinkle-25.6.0.dist-info/entry_points.txt
spelltinkle-25.6.0.dist-info/pbr.json
spelltinkle-25.6.0.dist-info/top_level.txt
spelltinkle-25.6.0.dist-info/RECORD
