Metadata-Version: 2.4
Name: spelltinkle
Version: 25.6.0
Summary: Text editor in a text terminal
Maintainer-email: Jens Jørgen Mortensen <jj@smoerhul.dk>
License:                     GNU GENERAL PUBLIC LICENSE
Project-URL: homepage, https://gitlab.com/jensj/spelltinkle
Project-URL: repository, https://gitlab.com/jensj/spelltinkle
Project-URL: docs, https://gitlab.com/jensj/spelltinkle
Project-URL: issues, https://gitlab.com/jensj/spelltinkle/-/issues
Classifier: Development Status :: 4 - Beta
Classifier: Environment :: Console
Classifier: Intended Audience :: Developers
Classifier: License :: OSI Approved :: GNU General Public License v3 or later (GPLv3+)
Classifier: Operating System :: Unix
Classifier: Programming Language :: Python :: 3
Classifier: Topic :: Text Editors :: Text Processing
Requires-Python: >=3.9
License-File: LICENSE
Requires-Dist: pygments
Requires-Dist: flake8
Requires-Dist: jedi
Requires-Dist: yapf
Requires-Dist: pyenchant
Requires-Dist: isort
Requires-Dist: imapclient
Provides-Extra: dev
Requires-Dist: pytest; extra == "dev"
Dynamic: license-file
